eric6_diff_merge/__init__.py
eric6_diff_merge/eric6_diff_merge.py
eric6_diff_merge-1.0.4.dist-info/LICENSE
eric6_diff_merge-1.0.4.dist-info/METADATA
eric6_diff_merge-1.0.4.dist-info/WHEEL
eric6_diff_merge-1.0.4.dist-info/top_level.txt
eric6_diff_merge-1.0.4.dist-info/RECORD
