Metadata-Version: 2.1
Name: eric6-diff-merge
Version: 1.0.4
Summary: python diff merge tool.
Home-page: https://github.com/625781186/eric6_diff_merge
Author: Lin JH
Author-email: 625781186@qq.com
License: GPL-3.0
Keywords: python、python diff merge
Platform: UNKNOWN
